LICENSE
MANIFEST.in
requirements.txt
setup.py
hgwebcommit/__init__.py
hgwebcommit/babel.cfg
hgwebcommit/forms.py
hgwebcommit/hgcmd.py
hgwebcommit/logger.py
hgwebcommit/main.py
hgwebcommit/messages.pot
hgwebcommit/utils.py
hgwebcommit/views.py
hgwebcommit.egg-info/PKG-INFO
hgwebcommit.egg-info/SOURCES.txt
hgwebcommit.egg-info/dependency_links.txt
hgwebcommit.egg-info/not-zip-safe
hgwebcommit.egg-info/requires.txt
hgwebcommit.egg-info/top_level.txt
hgwebcommit/actions/__init__.py
hgwebcommit/actions/base.py
hgwebcommit/actions/command.py
hgwebcommit/actions/commit.py
hgwebcommit/actions/decorators.py
hgwebcommit/actions/hello.py
hgwebcommit/actions/loaders.py
hgwebcommit/repository/__init__.py
hgwebcommit/repository/base.py
hgwebcommit/repository/dummy.py
hgwebcommit/repository/hg.py
hgwebcommit/static/css/base.css
hgwebcommit/static/img/favicon.ico
hgwebcommit/static/js/jquery-1.4.2.min.js
hgwebcommit/templates/add_unknown_confirm.html
hgwebcommit/templates/base.html
hgwebcommit/templates/base_site.html
hgwebcommit/templates/index.html
hgwebcommit/templates/submit.html
hgwebcommit/templates/actions/command.html
hgwebcommit/templates/actions/commit.html
hgwebcommit/translations/ja/LC_MESSAGES/messages.mo
hgwebcommit/translations/ja/LC_MESSAGES/messages.po
tests/__init__.py
tests/action_testcases.py