Metadata-Version: 1.0
Name: hgwebcommit
Version: 0.2
Summary: web based commit tool for mercurial
Home-page: http://bitbucket.org/tokibito/flask-hgwebcommit/
Author: Shinya Okano
Author-email: tokibito@gmail.com
License: UNKNOWN
Platform: UNKNOWN
Classifier: Development Status :: 3 - Alpha
Classifier: Environment :: Web Environment
Classifier: Intended Audience :: Developers
Classifier: License :: OSI Approved :: BSD License
Classifier: Operating System :: OS Independent
Classifier: Programming Language :: Python
Classifier: Topic :: Software Development :: Libraries :: Python Modules
